nbcx/__init__.py
nbcx/generate.py
nbcx/config/__init__.py
nbcx/config/base.py
nbcx/config/config.py
nbcx/config/context.py
nbcx/config/outputs.py
nbcx/config/parameters.py
nbcx/config/utils.py
nbcx/config/content/__init__.py
nbcx/config/content/base.py
nbcx/config/content/cover.py
nbcx/config/content/image.py
nbcx/config/content/pagebreak.py
nbcx/config/content/table_of_contents.py
nbcx/config/layout/__init__.py
nbcx/config/layout/base.py
nbcx/config/layout/common.py
nbcx/config/layout/page_number.py
nbcx/example/__init__.py
nbcx/example/code.py
nbcx/example/context.py
nbcx/example/cover.py
nbcx/example/markdown.py
nbcx/example/parameters.py
nbcx/extension/embedded.css
nbcx/extension/index.css
nbcx/extension/index.js
nbcx/extension/index.js.map
nbcx/extension/table-of-content.css
nbcx/old/__init__.py
nbcx/old/tags.py
nbcx/old/exporters/__init__.py
nbcx/old/exporters/html.py
nbcx/old/exporters/latex.py
nbcx/old/exporters/pdf.py
nbcx/old/exporters/template.py
nbcx/old/exporters/utils.py
nbcx/old/tests/__init__.py
nbcx/old/tests/test_import.py
nbcx/old/tests/test_parity.py
nbcx/old/utils/__init__.py
nbcx/old/utils/common.py
nbcx/old/utils/image.py
nbcx/old/utils/pandas.py
nbcx/old/utils/html/__init__.py
nbcx/old/utils/latex/__init__.py
nbcx/old/utils/resources/jupyter_style.css
nbcx/templates/nbcx/conf.json
nbcx/templates/nbcx/index.html.j2
nbcx/templates/nbcx/static/embedded.css
nbcx/templates/nbcx/static/embedded.js
nbcx/templates/nbcx/static/embedded.js.map
nbcx/templates/nbcx/static/global.css
nbcx/templates/nbcx/static/table-of-content.css
nbcx/templates/old/nbcx_base/jupyter_style.css
nbcx/templates/old/nbcx_base/nbcx.html.j2
nbcx/templates/old/nbcx_base/nbcx.tex.j2
nbcx/templates/old/nbcx_base/style.css
nbcx/templates/old/nbcx_template1_html/conf.json
nbcx/templates/old/nbcx_template1_html/index.html.j2
nbcx/templates/old/nbcx_template1_pdf/conf.json
nbcx/templates/old/nbcx_template1_pdf/index.tex.j2
nbcx/templates/old/nbcx_template2_html/conf.json
nbcx-0.1.2.dist-info/METADATA
nbcx-0.1.2.dist-info/WHEEL
nbcx-0.1.2.dist-info/licenses/LICENSE
nbcx-0.1.2.dist-info/RECORD
