Metadata-Version: 2.1
Name: nbcx
Version: 0.1.2
Summary: A framework for customizing NBConvert templates and building reports
Project-URL: repository, https://github.com/timkpaine/nbcx
Project-URL: homepage, https://github.com/timkpaine/nbcx
Author-email: Tim Paine <t.paine154@gmail.com>
License:                                  Apache License
License-File: LICENSE
Keywords: Jupyter,JupyterLab,Notebook,Notebooks,Report,Reporting,Reports
Classifier: Development Status :: 4 - Beta
Classifier: Framework :: Jupyter
Classifier: Framework :: Jupyter :: JupyterLab
Classifier: License :: OSI Approved :: Apache Software License
Classifier: Programming Language :: Python
Classifier: Programming Language :: Python :: 3
Classifier: Programming Language :: Python :: 3.8
Classifier: Programming Language :: Python :: 3.9
Classifier: Programming Language :: Python :: 3.10
Classifier: Programming Language :: Python :: 3.11
Classifier: Programming Language :: Python :: 3.12
Requires-Python: >=3.8
Requires-Dist: dominate
Requires-Dist: ipywidgets
Requires-Dist: nbformat
Requires-Dist: notebook
Requires-Dist: omegaconf
Requires-Dist: pydantic
Provides-Extra: develop
Requires-Dist: black>=23; extra == 'develop'
Requires-Dist: check-manifest; extra == 'develop'
Requires-Dist: matplotlib; extra == 'develop'
Requires-Dist: pandas; extra == 'develop'
Requires-Dist: perspective-python; extra == 'develop'
Requires-Dist: pytest; extra == 'develop'
Requires-Dist: pytest-cov; extra == 'develop'
Requires-Dist: ruff; extra == 'develop'
Requires-Dist: seaborn; extra == 'develop'
Provides-Extra: test
Requires-Dist: pytest; extra == 'test'
Requires-Dist: pytest-cov; extra == 'test'
